RPi/__init__.py
RPi/GPIO/__init__.py
rpi_lgpio-0.6.dist-info/LICENSE.txt
rpi_lgpio-0.6.dist-info/METADATA
rpi_lgpio-0.6.dist-info/WHEEL
rpi_lgpio-0.6.dist-info/top_level.txt
rpi_lgpio-0.6.dist-info/RECORD
