Metadata-Version: 2.1
Name: rpi-lgpio
Version: 0.6
Summary: A compatibility shim between RPi.GPIO and lgpio
Home-page: https://rpi-lgpio.readthedocs.io/
Author: Dave Jones
Author-email: dave@waveform.org.uk
License: BSD-3-Clause
Project-URL: Documentation, https://rpi-lgpio.readthedocs.io/
Project-URL: Source Code, https://github.com/waveform80/rpi-lgpio
Project-URL: Issue Tracker, https://github.com/waveform80/rpi-lgpio/issues
Keywords: raspberrypi gpio lgpio rpi-gpio
Classifier: Development Status :: 3 - Alpha
Classifier: Intended Audience :: Developers
Classifier: Topic :: System :: Hardware
Classifier: License :: OSI Approved :: BSD License
Classifier: Programming Language :: Python :: 3
Classifier: Programming Language :: Python :: 3.7
Classifier: Programming Language :: Python :: 3.8
Classifier: Programming Language :: Python :: 3.9
Classifier: Programming Language :: Python :: 3.10
Classifier: Programming Language :: Python :: 3.11
Classifier: Programming Language :: Python :: Implementation :: PyPy
Requires-Python: >=3.7
License-File: LICENSE.txt
Requires-Dist: lgpio>=0.1.0.1
Provides-Extra: test
Requires-Dist: pytest; extra == "test"
Requires-Dist: pytest-cov; extra == "test"
Provides-Extra: doc
Requires-Dist: sphinx; extra == "doc"
Requires-Dist: sphinx-rtd-theme; extra == "doc"
